chainy/__init__.py
chainy/config.py
chainy/llm.py
chainy/model.py
chainy-0.1.0.dist-info/LICENSE
chainy-0.1.0.dist-info/METADATA
chainy-0.1.0.dist-info/WHEEL
chainy-0.1.0.dist-info/top_level.txt
chainy-0.1.0.dist-info/RECORD
